pyaware/__init__.py
pyaware/__main__.py
pyaware/aggregations.py
pyaware/commands.py
pyaware/config.py
pyaware/exceptions.py
pyaware/logger.py
pyaware/maintenance.py
pyaware/meta.py
pyaware/parameters.py
pyaware/profiler.py
pyaware/reporting.py
pyaware/transformations.py
pyaware/watchdog.py
pyaware/azure/__init__.py
pyaware/azure/client.py
pyaware/azure/config.py
pyaware/controllers/__init__.py
pyaware/controllers/comap.py
pyaware/controllers/commands.py
pyaware/controllers/modbus.py
pyaware/controllers/snmp.py
pyaware/controllers/solar_qube.py
pyaware/controllers/sp_pro.py
pyaware/controllers/translator.py
pyaware/controllers/imac2/__init__.py
pyaware/controllers/imac2/ensham_schema.yaml
pyaware/controllers/imac2/master.py
pyaware/controllers/imac2/topology.py
pyaware/data_types/__init__.py
pyaware/data_types/abc.py
pyaware/data_types/common.py
pyaware/data_types/modbus.py
pyaware/data_types/snmp.py
pyaware/devices/__init__.py
pyaware/devices/abb/__init__.py
pyaware/devices/abb/ekip_com_tmax.yaml
pyaware/devices/abb/ekipelsig.yaml
pyaware/devices/abb/emax2.yaml
pyaware/devices/abb/m2m.yaml
pyaware/devices/abb/ret615.jinja2
pyaware/devices/abb/rex640.jinja2
pyaware/devices/aerl/__init__.py
pyaware/devices/aerl/coolmax_srx_600.yaml
pyaware/devices/ampcontrol/__init__.py
pyaware/devices/ampcontrol/hpb.jinja2
pyaware/devices/ampcontrol/ipb.yaml
pyaware/devices/ampcontrol/ipc.yaml
pyaware/devices/ampcontrol/ipd.yaml
pyaware/devices/ampcontrol/ipm.yaml
pyaware/devices/ampcontrol/austech/__init__.py
pyaware/devices/ampcontrol/austech/touchpro.jinja2
pyaware/devices/ampcontrol/austech/touchpro.yaml
pyaware/devices/ampcontrol/hst/__init__.py
pyaware/devices/ampcontrol/hst/substation_plc.yaml
pyaware/devices/ampcontrol/imac/__init__.py
pyaware/devices/ampcontrol/imac/aim_parameter_spec.yaml
pyaware/devices/ampcontrol/imac/di4_parameter_spec.yaml
pyaware/devices/ampcontrol/imac/do4_4_parameter_spec.yaml
pyaware/devices/ampcontrol/imac/gasguard2_parameter_spec.yaml
pyaware-7.1.0.dist-info/METADATA
pyaware-7.1.0.dist-info/WHEEL
pyaware-7.1.0.dist-info/top_level.txt
pyaware-7.1.0.dist-info/RECORD
