Metadata-Version: 2.1
Name: pyaware
Version: 7.1.0
Summary: Framework for reading connected devices and publishing to the AWARE cloud
Author: Ryan Parry-Jones
Author-email: Ryan.Parry-Jones@ampcontrolgroup.com
Classifier: Intended Audience :: Manufacturing
Classifier: Operating System :: Microsoft :: Windows
Classifier: Programming Language :: Python :: 3 :: Only
Requires-Python: >=3.7.0
Requires-Dist: aiohttp ==3.6.2
Requires-Dist: aiomodbus ==0.5.2
Requires-Dist: aiosqlite ==0.17.0
Requires-Dist: amqtt-pazzarpj ==0.10.1.dev1
Requires-Dist: async-timeout ==3.0.1
Requires-Dist: attrs ==23.1.0
Requires-Dist: azure-iot-device ==2.12.0
Requires-Dist: beautifulsoup4 ==4.9.3
Requires-Dist: certifi ==2023.5.7
Requires-Dist: cffi ==1.15.1
Requires-Dist: chardet ==3.0.4
Requires-Dist: cryptography ==2.8
Requires-Dist: deprecation ==2.1.0
Requires-Dist: docopt ==0.6.2
Requires-Dist: idna ==2.10
Requires-Dist: ifaddr ==0.1.7
Requires-Dist: importlib-metadata ==6.7.0
Requires-Dist: janus ==0.5.0
Requires-Dist: jinja2 ==3.1.2
Requires-Dist: markupsafe ==2.1.1
Requires-Dist: multidict ==4.7.6
Requires-Dist: packaging ==21.3
Requires-Dist: paho-mqtt ==1.6.1
Requires-Dist: passlib ==1.7.4
Requires-Dist: puresnmp ==1.10.2.post1
Requires-Dist: pycparser ==2.21
Requires-Dist: pydantic ==1.6.1
Requires-Dist: pyjwt ==1.7.1
Requires-Dist: pymodbus ==2.3.0
Requires-Dist: pyparsing ==3.1.0
Requires-Dist: pyserial ==3.5
Requires-Dist: pyserial-asyncio ==0.4
Requires-Dist: pysocks ==1.7.1
Requires-Dist: python-dateutil ==2.8.1
Requires-Dist: pyyaml ==5.4.1
Requires-Dist: requests ==2.25.0
Requires-Dist: requests-unixsocket ==0.3.0
Requires-Dist: ruamel-yaml ==0.18.2
Requires-Dist: ruamel-yaml-clib ==0.2.8
Requires-Dist: six ==1.16.0
Requires-Dist: soupsieve ==2.4.1
Requires-Dist: t61codec ==2.0.0
Requires-Dist: transitions ==0.8.7
Requires-Dist: typing-extensions ==4.7.1
Requires-Dist: urllib3 ==1.26.16
Requires-Dist: verlib ==0.1
Requires-Dist: websockets ==9.1
Requires-Dist: yarl ==1.9.2
Requires-Dist: zipp ==3.15.0
